{
  "seed": 42,
  "use_cuda": true,
  "results_dir": "results",
  "x_min": 0.0,
  "x_max": 1.0,
  "y_min": 0.0,
  "y_max": 1.0,
  "nu": 0.01,
  "kappa": 0.01,
  "D": 0.01,
  "alpha_e": 0.4,
  "beta_tc": 0.5,
  "gamma_ct": 0.3,
  "n_f": 10000,
  "n_data": 6000,
  "n_bc_each": 600,
  "train_ratio": 0.7,
  "input_dim": 2,
  "output_dim": 5,
  "hidden_dim": 128,
  "num_blocks": 6,
  "activation": "tanh",
  "use_learnable_alpha": true,
  "dropout": 0.0,
  "adam_epochs": 5000,
  "adam_lr": 0.001,
  "weight_decay": 1e-08,
  "print_every": 100,
  "grad_clip": 10.0,
  "use_scheduler": true,
  "scheduler_step_size": 1000,
  "scheduler_gamma": 0.7,
  "use_lbfgs": true,
  "lbfgs_max_iter": 300,
  "lbfgs_lr": 1.0,
  "w_pde": 1.0,
  "w_bc": 10.0,
  "w_data": 10.0,
  "pde_batch_size": 256,
  "data_batch_size": 1024,
  "bc_batch_size": 1024,
  "predict_batch_size": 4096,
  "source_chunk_size": 256,
  "test_nx": 200,
  "test_ny": 200,
  "dpi": 300,
  "empty_cache_every": 100
}